mobio/libs/m_scheduler_partitioning/__init__.py
mobio/libs/m_scheduler_partitioning/m_scheduler.py
mobio/libs/m_scheduler_partitioning/scheduler_models/__init__.py
mobio/libs/m_scheduler_partitioning/scheduler_models/base_model.py
mobio/libs/m_scheduler_partitioning/scheduler_models/db_manager.py
mobio/libs/m_scheduler_partitioning/scheduler_models/scheduler_state_model.py
m_scheduler_partitioning-0.1.4.dist-info/METADATA
m_scheduler_partitioning-0.1.4.dist-info/WHEEL
m_scheduler_partitioning-0.1.4.dist-info/top_level.txt
m_scheduler_partitioning-0.1.4.dist-info/RECORD
